Metadata-Version: 1.1
Name: netatmo-client
Version: 0.0.3
Summary: A client library for Netatmo
Home-page: http://github.com/antechrestos/python-netatmo-client
Author: Benjamin Einaudi
Author-email: antechrestos@gmail.com
License: UNKNOWN
Platform: UNKNOWN
Classifier: Programming Language :: Python
Classifier: Natural Language :: English
Classifier: Operating System :: OS Independent
Classifier: Programming Language :: Python :: 2.7
Classifier: Topic :: Communications
